nbdev_othmane_test/__init__.py
nbdev_othmane_test/_modidx.py
nbdev_othmane_test/card.py
nbdev_othmane_test/core.py
nbdev_othmane_test/deck.py
nbdev_othmane_test-0.0.1.dist-info/LICENSE
nbdev_othmane_test-0.0.1.dist-info/METADATA
nbdev_othmane_test-0.0.1.dist-info/WHEEL
nbdev_othmane_test-0.0.1.dist-info/entry_points.txt
nbdev_othmane_test-0.0.1.dist-info/top_level.txt
nbdev_othmane_test-0.0.1.dist-info/RECORD
